leeroo_client/__init__.py
leeroo_client/client.py
leeroo_client-0.0.2.dist-info/LICENSE
leeroo_client-0.0.2.dist-info/METADATA
leeroo_client-0.0.2.dist-info/WHEEL
leeroo_client-0.0.2.dist-info/top_level.txt
leeroo_client-0.0.2.dist-info/RECORD
