Metadata-Version: 2.1
Name: leeroo-client
Version: 0.0.2
Summary: A client library for Leeroo Workflow Management
Author-email: Leeroo Team <support@leeroo.com>
License: Apache License
Project-URL: homepage, https://github.com/Leeroo-AI/leeroo-client
Project-URL: repository, https://github.com/Leeroo-AI/leeroo-client
Keywords: training,LLM,Leeroo,fine-tuning,evaluation,deployment
License-File: LICENSE
Requires-Dist: requests
